portrait/__init__.py
portrait/core.py
portrait-0.0.5b0.dist-info/METADATA
portrait-0.0.5b0.dist-info/WHEEL
portrait-0.0.5b0.dist-info/licenses/LICENSE
portrait-0.0.5b0.dist-info/RECORD
