Metadata-Version: 2.3
Name: portrait
Version: 0.0.5b0
Summary: Compute and visualize observations phase coverage
Author: Lionel Garcia
License-Expression: MIT
License-File: LICENSE
Keywords: astronomy,image processing,jax
Classifier: Development Status :: 4 - Beta
Classifier: Programming Language :: Python
Classifier: Programming Language :: Python :: 3
Requires-Python: >=3.8
Requires-Dist: jax>=0.2.25
Requires-Dist: jaxlib
Requires-Dist: numpy>=1.23.5
Provides-Extra: dev
Requires-Dist: black; extra == 'dev'
Requires-Dist: isort; extra == 'dev'
Requires-Dist: pytest; extra == 'dev'
Provides-Extra: docs
Requires-Dist: black; extra == 'docs'
Requires-Dist: docutils; extra == 'docs'
Requires-Dist: jupyterlab; extra == 'docs'
Requires-Dist: lightkurve; extra == 'docs'
Requires-Dist: matplotlib; extra == 'docs'
Requires-Dist: myst-nb; extra == 'docs'
Requires-Dist: myst-parser; extra == 'docs'
Requires-Dist: sphinx; extra == 'docs'
Requires-Dist: sphinx-book-theme; extra == 'docs'
Requires-Dist: sphinx-copybutton; extra == 'docs'
Requires-Dist: twine; extra == 'docs'
